keios_protocol_tesseract/__init__.py
keios_protocol_tesseract/flatbuffers/TesseractMessage.py
keios_protocol_tesseract/flatbuffers/TesseractMessageType.py
keios_protocol_tesseract/flatbuffers/TesseractOcrRequest.py
keios_protocol_tesseract/flatbuffers/TesseractOcrResponse.py
keios_protocol_tesseract-1.1.0.dist-info/WHEEL
keios_protocol_tesseract-1.1.0.dist-info/METADATA
keios_protocol_tesseract-1.1.0.dist-info/RECORD
