Metadata-Version: 2.1
Name: keios-protocol-tesseract
Version: 1.1.0
Summary: 
Author: Leftshift One
Author-email: contact@leftshift.one
Requires-Python: >=3.7,<4.0
Classifier: Programming Language :: Python :: 3
Classifier: Programming Language :: Python :: 3.7
Requires-Dist: flatbuffers (==1.11)
